BDSpaceVis/__init__.py
BDSpaceVis/_version.py
BDSpaceVis/coordinate_system.py
BDSpaceVis/curves.py
BDSpaceVis/fields.py
BDSpaceVis/figures.py
BDSpaceVis/generators.py
BDSpaceVis/space.py
BDSpaceVis/utils.py
BDSpaceVis-0.1.8.dist-info/LICENSE
BDSpaceVis-0.1.8.dist-info/METADATA
BDSpaceVis-0.1.8.dist-info/NOTICE
BDSpaceVis-0.1.8.dist-info/WHEEL
BDSpaceVis-0.1.8.dist-info/top_level.txt
BDSpaceVis-0.1.8.dist-info/RECORD
